minigrid/__init__.py
minigrid/benchmark.py
minigrid/manual_control.py
minigrid/minigrid_env.py
minigrid/py.typed
minigrid/wrappers.py
minigrid/core/__init__.py
minigrid/core/actions.py
minigrid/core/constants.py
minigrid/core/grid.py
minigrid/core/mission.py
minigrid/core/roomgrid.py
minigrid/core/world_object.py
minigrid/envs/__init__.py
minigrid/envs/blockedunlockpickup.py
minigrid/envs/crossing.py
minigrid/envs/distshift.py
minigrid/envs/doorkey.py
minigrid/envs/dynamicobstacles.py
minigrid/envs/empty.py
minigrid/envs/fetch.py
minigrid/envs/fourrooms.py
minigrid/envs/gotodoor.py
minigrid/envs/gotoobject.py
minigrid/envs/keycorridor.py
minigrid/envs/lavagap.py
minigrid/envs/lockedroom.py
minigrid/envs/memory.py
minigrid/envs/multiroom.py
minigrid/envs/obstructedmaze.py
minigrid/envs/obstructedmaze_v1.py
minigrid/envs/playground.py
minigrid/envs/putnear.py
minigrid/envs/redbluedoors.py
minigrid/envs/unlock.py
minigrid/envs/unlockpickup.py
minigrid/envs/babyai/__init__.py
minigrid/envs/babyai/goto.py
minigrid/envs/babyai/open.py
minigrid/envs/babyai/other.py
minigrid/envs/babyai/pickup.py
minigrid/envs/babyai/putnext.py
minigrid/envs/babyai/synth.py
minigrid/envs/babyai/unlock.py
minigrid/envs/babyai/core/__init__.py
minigrid/envs/babyai/core/levelgen.py
minigrid/envs/babyai/core/roomgrid_level.py
minigrid/envs/babyai/core/verifier.py
minigrid/envs/wfc/__init__.py
minigrid/envs/wfc/config.py
minigrid/envs/wfc/graphtransforms.py
minigrid/envs/wfc/wfcenv.py
minigrid/envs/wfc/wfclogic/__init__.py
minigrid/envs/wfc/wfclogic/adjacency.py
minigrid/envs/wfc/wfclogic/control.py
minigrid/envs/wfc/wfclogic/patterns.py
minigrid/envs/wfc/wfclogic/solver.py
minigrid/envs/wfc/wfclogic/tiles.py
minigrid/envs/wfc/wfclogic/utilities.py
minigrid/utils/__init__.py
minigrid/utils/baby_ai_bot.py
minigrid/utils/rendering.py
minigrid-3.0.0.dist-info/LICENSE
minigrid-3.0.0.dist-info/METADATA
minigrid-3.0.0.dist-info/WHEEL
minigrid-3.0.0.dist-info/top_level.txt
minigrid-3.0.0.dist-info/RECORD
