Metadata-Version: 2.1
Name: minigrid
Version: 3.0.0
Summary: Minimalistic gridworld reinforcement learning environments.
Author-email: Farama Foundation <contact@farama.org>
License: MIT License
Project-URL: Homepage, https://farama.org
Project-URL: Repository, https://minigrid.farama.org/
Project-URL: Documentation, https://minigrid.farama.org/
Project-URL: Bug Report, https://github.com/Farama-Foundation/Minigrid/issues
Keywords: Memory, Environment, Agent, RL, Gymnasium
Classifier: Development Status :: 4 - Beta
Classifier: License :: OSI Approved :: MIT License
Classifier: Programming Language :: Python :: 3
Classifier: Programming Language :: Python :: 3.7
Classifier: Programming Language :: Python :: 3.8
Classifier: Programming Language :: Python :: 3.9
Classifier: Programming Language :: Python :: 3.10
Classifier: Programming Language :: Python :: 3.11
Classifier: Intended Audience :: Science/Research
Classifier: Topic :: Scientific/Engineering :: Artificial Intelligence
Requires-Python: >=3.7
License-File: LICENSE
Requires-Dist: numpy>=1.18.0
Requires-Dist: gymnasium>=0.28.1
Requires-Dist: pygame>=2.4.0
Provides-Extra: testing
Requires-Dist: pytest>=7.0.1; extra == "testing"
Requires-Dist: pytest-mock>=3.10.0; extra == "testing"
Requires-Dist: matplotlib>=3.0; extra == "testing"
Provides-Extra: wfc
Requires-Dist: networkx; extra == "wfc"
Requires-Dist: imageio>=2.31.1; extra == "wfc"
